fiddler/VERSION
fiddler/__init__.py
fiddler/configs.py
fiddler/connection.py
fiddler/decorators.py
fiddler/exceptions.py
fiddler/version.py
fiddler/constants/__init__.py
fiddler/constants/alert_rule.py
fiddler/constants/baseline.py
fiddler/constants/common.py
fiddler/constants/dataset.py
fiddler/constants/events.py
fiddler/constants/job.py
fiddler/constants/model.py
fiddler/constants/model_deployment.py
fiddler/constants/xai.py
fiddler/entities/__init__.py
fiddler/entities/alert_record.py
fiddler/entities/alert_rule.py
fiddler/entities/base.py
fiddler/entities/baseline.py
fiddler/entities/custom_expression.py
fiddler/entities/dataset.py
fiddler/entities/events.py
fiddler/entities/file.py
fiddler/entities/job.py
fiddler/entities/model.py
fiddler/entities/model_artifact.py
fiddler/entities/model_deployment.py
fiddler/entities/organization.py
fiddler/entities/project.py
fiddler/entities/surrogate.py
fiddler/entities/user.py
fiddler/entities/webhook.py
fiddler/entities/xai.py
fiddler/libs/__init__.py
fiddler/libs/aws.py
fiddler/libs/http_client.py
fiddler/libs/json_encoder.py
fiddler/libs/semver.py
fiddler/packtools/__init__.py
fiddler/packtools/gem.py
fiddler/packtools/keras_ig_helpers.py
fiddler/packtools/project_attributions_helpers.py
fiddler/packtools/template_model.py
fiddler/schemas/__init__.py
fiddler/schemas/alert_record.py
fiddler/schemas/alert_rule.py
fiddler/schemas/base.py
fiddler/schemas/baseline.py
fiddler/schemas/custom_expression.py
fiddler/schemas/custom_features.py
fiddler/schemas/dataset.py
fiddler/schemas/events.py
fiddler/schemas/file.py
fiddler/schemas/filter_query.py
fiddler/schemas/job.py
fiddler/schemas/model.py
fiddler/schemas/model_deployment.py
fiddler/schemas/model_schema.py
fiddler/schemas/model_spec.py
fiddler/schemas/model_task_params.py
fiddler/schemas/organization.py
fiddler/schemas/project.py
fiddler/schemas/response.py
fiddler/schemas/server_info.py
fiddler/schemas/user.py
fiddler/schemas/webhook.py
fiddler/schemas/xai.py
fiddler_client-3.10.0.dist-info/LICENSE.txt
fiddler_client-3.10.0.dist-info/METADATA
fiddler_client-3.10.0.dist-info/WHEEL
fiddler_client-3.10.0.dist-info/top_level.txt
fiddler_client-3.10.0.dist-info/RECORD
