Metadata-Version: 2.1
Name: fiddler-client
Version: 3.10.0
Summary: Python client for Fiddler Platform
Home-page: https://fiddler.ai
Author: Fiddler Labs
License: UNKNOWN
Platform: UNKNOWN
Classifier: Programming Language :: Python :: 3
Classifier: License :: OSI Approved :: Apache Software License
Classifier: Operating System :: OS Independent
Requires-Python: >3.9.0
License-File: LICENSE.txt
Requires-Dist: deprecated (==1.2.18)
Requires-Dist: pandas (>=1.2.5)
Requires-Dist: pip (>=21.0)
Requires-Dist: pyarrow (>=15.0.0)
Requires-Dist: pydantic (>=1.10.17)
Requires-Dist: pyyaml
Requires-Dist: requests-toolbelt
Requires-Dist: requests (<3)
Requires-Dist: simplejson (>=3.17.0)
Requires-Dist: tqdm
Requires-Dist: typing-extensions (<5,>=4.6.0)
